{
	"info": {
		"_postman_id": "f584884c-45fd-47cd-8d38-4cc1f1d16d27",
		"name": "RAG",
		"schema": "https://schema.getpostman.com/json/collection/v2.1.0/collection.json",
		"_exporter_id": "38349989",
		"_collection_link": "https://learnai-4104.postman.co/workspace/LearnAI-Workspace~21f3c471-b82a-4d3c-825d-6b17f1847fee/collection/38349989-f584884c-45fd-47cd-8d38-4cc1f1d16d27?action=share&source=collection_link&creator=38349989"
	},
	"item": [
		{
			"name": "welcome",
			"request": {
				"method": "GET",
				"header": [],
				"url": {
					"raw": "{{url}}/api/v1/",
					"host": [
						"{{url}}"
					],
					"path": [
						"api",
						"v1",
						""
					]
				}
			},
			"response": []
		},
		{
			"name": "upload",
			"request": {
				"method": "POST",
				"header": [
					{
						"key": "Authorization",
						"value": "Bearer {{token}}",
						"type": "text"
					}
				],
				"body": {
					"mode": "formdata",
					"formdata": [
						{
							"key": "files",
							"type": "file",
							"src": [
								"/C:/Users/FADI/Downloads/sajalni_351212588176632.pdf",
								"/C:/Users/FADI/Downloads/Fedi-Ben-Mahfoudh-FlowCV-Resume-20250213.pdf"
							]
						}
					]
				},
				"url": {
					"raw": "{{url}}/api/v1/data/upload",
					"host": [
						"{{url}}"
					],
					"path": [
						"api",
						"v1",
						"data",
						"upload"
					]
				}
			},
			"response": []
		},
		{
			"name": "upload_to_existing_conversation",
			"request": {
				"method": "POST",
				"header": [
					{
						"key": "Authorization",
						"value": "Bearer {{token}}",
						"type": "text"
					}
				],
				"body": {
					"mode": "formdata",
					"formdata": [
						{
							"key": "files",
							"type": "file",
							"src": "/C:/Users/FADI/Downloads/sajalni_351212588176632.pdf"
						}
					]
				},
				"url": {
					"raw": "{{url}}/api/v1/data/upload/:conv_id",
					"host": [
						"{{url}}"
					],
					"path": [
						"api",
						"v1",
						"data",
						"upload",
						":conv_id"
					],
					"variable": [
						{
							"key": "conv_id",
							"value": "68286d009683acd530f3e26d"
						}
					]
				}
			},
			"response": []
		},
		{
			"name": "process",
			"request": {
				"method": "POST",
				"header": [
					{
						"key": "Authorization",
						"value": "Bearer {{token}}",
						"type": "text"
					}
				],
				"body": {
					"mode": "raw",
					"raw": "{\r\n    // \"file_id\" : ,\r\n    \"chunk_size\" : 400,\r\n    \"overlap_size\" : 50,\r\n    \"do_reset\" : 1\r\n}",
					"options": {
						"raw": {
							"language": "json"
						}
					}
				},
				"url": {
					"raw": "{{url}}/api/v1/data/process/user1/conv2",
					"host": [
						"{{url}}"
					],
					"path": [
						"api",
						"v1",
						"data",
						"process",
						"user1",
						"conv2"
					]
				}
			},
			"response": []
		},
		{
			"name": "push_index_nlp",
			"request": {
				"method": "POST",
				"header": [
					{
						"key": "Authorization",
						"value": "Bearer {{token}}",
						"type": "text"
					}
				],
				"body": {
					"mode": "raw",
					"raw": "{\r\n    // \"do_reset\" : 1,\r\n    // \"embedding_size\" : 3072\r\n}",
					"options": {
						"raw": {
							"language": "json"
						}
					}
				},
				"url": {
					"raw": "{{url}}/api/v1/nlp/index/push/:conversation_id",
					"host": [
						"{{url}}"
					],
					"path": [
						"api",
						"v1",
						"nlp",
						"index",
						"push",
						":conversation_id"
					],
					"variable": [
						{
							"key": "conversation_id",
							"value": "682af118c452052c12e5ce58"
						}
					]
				}
			},
			"response": []
		},
		{
			"name": "search_index_nlp",
			"request": {
				"method": "POST",
				"header": [
					{
						"key": "Authorization",
						"value": "Bearer {{token}}",
						"type": "text"
					}
				],
				"body": {
					"mode": "raw",
					"raw": "{\r\n    \"text\" : \"What is the two documents\"\r\n}",
					"options": {
						"raw": {
							"language": "json"
						}
					}
				},
				"url": {
					"raw": "{{url}}/api/v1/nlp/index/search/:conversation_id",
					"host": [
						"{{url}}"
					],
					"path": [
						"api",
						"v1",
						"nlp",
						"index",
						"search",
						":conversation_id"
					],
					"variable": [
						{
							"key": "conversation_id",
							"value": ""
						}
					]
				}
			},
			"response": []
		},
		{
			"name": "rag_answer_nlp",
			"request": {
				"method": "POST",
				"header": [
					{
						"key": "Authorization",
						"value": "Bearer {{token}}",
						"type": "text"
					}
				],
				"body": {
					"mode": "raw",
					"raw": "{\r\n    \"text\" : \"how can i do the exercices with hive\"\r\n    // \"limit\" : 5\r\n}",
					"options": {
						"raw": {
							"language": "json"
						}
					}
				},
				"url": {
					"raw": "{{url}}/api/v1/nlp/index/answer/:conversation_id",
					"host": [
						"{{url}}"
					],
					"path": [
						"api",
						"v1",
						"nlp",
						"index",
						"answer",
						":conversation_id"
					],
					"variable": [
						{
							"key": "conversation_id",
							"value": "682af118c452052c12e5ce58"
						}
					]
				}
			},
			"response": []
		},
		{
			"name": "info_index_nlp",
			"protocolProfileBehavior": {
				"disableBodyPruning": true
			},
			"request": {
				"method": "GET",
				"header": [
					{
						"key": "Authorization",
						"value": "Bearer {{token}}",
						"type": "text"
					}
				],
				"body": {
					"mode": "raw",
					"raw": "",
					"options": {
						"raw": {
							"language": "json"
						}
					}
				},
				"url": {
					"raw": "{{url}}/api/v1/nlp/index/info/:conversation_id",
					"host": [
						"{{url}}"
					],
					"path": [
						"api",
						"v1",
						"nlp",
						"index",
						"info",
						":conversation_id"
					],
					"variable": [
						{
							"key": "conversation_id",
							"value": ""
						}
					]
				}
			},
			"response": []
		}
	],
	"variable": [
		{
			"key": "url",
			"value": "localhost:5000",
			"type": "default"
		}
	]
}